kpra_covid/__init__.py
kpra_covid/covid_tracker.py
kpra_covid/main.py
kpra_covid/utils.py
kpra_covid-0.0.1.dist-info/METADATA
kpra_covid-0.0.1.dist-info/WHEEL
kpra_covid-0.0.1.dist-info/top_level.txt
kpra_covid-0.0.1.dist-info/RECORD
