Metadata-Version: 2.1
Name: kpra-covid
Version: 0.0.1
Summary: Covid count tracker
Author: Kiran Prasannadas
Author-email: kiranpdas123@gmail.com
Keywords: covid
Classifier: Development Status :: 1 - Planning
Classifier: Intended Audience :: Developers
Classifier: Programming Language :: Python :: 3
Classifier: Operating System :: Unix
Classifier: Operating System :: MacOS :: MacOS X
Classifier: Operating System :: Microsoft :: Windows
Requires-Dist: pandas
